{
  "updated": "2026-06-22T05:28:45.100095+00:00",
  "count": 12,
  "sources": {
    "Fightful": "ok (2 AEW items)",
    "Wrestling Observer": "ok (6 AEW items)",
    "PWTorch": "ok (6 AEW items)",
    "POST Wrestling": "ok (6 AEW items)",
    "PWInsider": "FAILED (HTTP Error 404: Not Found)",
    "Wrestling Inc": "ok (6 AEW items)",
    "ProWrestling.net": "ok (6 AEW items)"
  },
  "items": [
    {
      "src": "PWTorch",
      "h": "FREE PODCAST 6/21 – WKPWP AEW Dynamite Post-Show – 5 Yrs Ago: AEW Dynamite Roundtable Review of latest Friday Night Dynamite plus preview of Saturday’s Special Dynamite with Omega vs. Jungle Boy (108 min.)",
      "p": "SHOW SUMMARY: In this week’s 5 Yrs Ago Flashback episode of the Wade Keller Pro Wrestling Post-show (6-23-2021), PWTorch editor Wade Keller sets the table with some talk about AEW’s schedule and...",
      "link": "https://www.pwtorch.com/site/2026/06/21/free-podcast-6-21-wkpwp-aew-dynamite-post-show-5-yrs-ago-aew-dynamite-roundtable-review-of-latest-friday-night-dynamite-plus-preview-of-saturdays-special-dynamite-with-om/",
      "t": "54m",
      "dt": "2026-06-22T04:34:09+00:00"
    },
    {
      "src": "Wrestling Observer",
      "h": "Champion issues tag team challenge for AEW x NJPW Forbidden Door",
      "p": "A challenge has been thrown out by a NJPW wrestler. HENARE, who recently won the IWGP Tag Team titles with Great-O-Khan, issued the challenge on social media Sunday. “O-Khan and I are ready for...",
      "link": "https://www.f4wonline.com/news/aew/champion-issues-tag-team-challenge-for-aew-x-njpw-forbidden-door/",
      "t": "1h",
      "dt": "2026-06-22T03:43:10+00:00"
    },
    {
      "src": "Fightful",
      "h": "WWE, AEW, TNA, NJPW Wrestler Injury Report List: Expected Returns, Inactives | Fightful",
      "p": "Fightful.com will keep a running injury report and inactive list and update each accordingly. You can also see our updated contract expiration list at this link. WWE RAW Bronson Reed: Reed...",
      "link": "https://www.fightful.com/wrestling-news/wwe-impact-njpw-roh-injury-report-expected-returns-more/",
      "t": "3h",
      "dt": "2026-06-22T02:09:00+00:00"
    },
    {
      "src": "PWTorch",
      "h": "AEW COLLISION HITS & MISSES (6/20/26): Maya World shocks Athena, Juice strikes gold in his segment, Statlander keeps building momentum",
      "p": "To help add context, my “Hits” are ordered from best to worst. With that said, let’s move into the high points of this week’s episode, starting with the most significant moments. HITS MAYA WORLD...",
      "link": "https://www.pwtorch.com/site/2026/06/21/aew-collision-hits-misses-6-20-26-maya-world-shocks-athena-juice-strikes-gold-in-his-segment-statlander-keeps-building-momentum/",
      "t": "3h",
      "dt": "2026-06-22T01:53:06+00:00"
    },
    {
      "src": "POST Wrestling",
      "h": "NWA Podcast: PredictionPalooza!!! | June 2026",
      "p": "The NWA Podcast is joined by Brandon Thurston to break down WWE/AEW TV ratings and top draws so far in 2026. Plus, predictions for WWE NOC, NXT GAB, AEW Forbidden Door, and TNA Slammiversary. The...",
      "link": "https://www.postwrestling.com/2026/06/21/nwa-podcast-predictionpalooza-june-2026/",
      "t": "3h",
      "dt": "2026-06-22T01:38:35+00:00"
    },
    {
      "src": "Fightful",
      "h": "Shota Umino Thinks AEW Looks Down On IWGP, Wants To Correct Course",
      "p": "Ahead of AEW x NJPW Forbidden Door, IWGP Heavyweight Champion Yota Tsuji suggested boycotting the event given how AEW had treated the champion over the years, noting that the title had been...",
      "link": "https://www.fightful.com/wrestling-news/shota-umino-thinks-aew-looks-down-on-iwgp-wants-to-correct-course/",
      "t": "5h",
      "dt": "2026-06-21T23:49:24+00:00"
    },
    {
      "src": "Wrestling Inc",
      "h": "Bobby Cruise Looks Back On His Start In ROH",
      "p": "Bobby Cruise looks back at his start in Ring of Honor, and reveals that it was not without controversy, as he replaced a former ECW name to get the job",
      "link": "https://www.wrestlinginc.com/2197277/bobby-cruise-looks-back-start-roh/",
      "t": "8h",
      "dt": "2026-06-21T21:00:00+00:00"
    },
    {
      "src": "Wrestling Inc",
      "h": "AEW's Private Party Injured In Same Match",
      "p": "Call it a cawinkadink, but it appears AEW's Private Party members are both out with the same injuries during the same match, according to reports.",
      "link": "https://www.wrestlinginc.com/2198477/aew-private-party-injured-same-match/",
      "t": "9h",
      "dt": "2026-06-21T19:30:15+00:00"
    },
    {
      "src": "Wrestling Observer",
      "h": "AEW x NJPW Forbidden Door 2026 betting odds released",
      "p": "Betting odds are now available for six matches scheduled for AEW x NJPW Forbidden Door. The pay-per-view is scheduled for Sunday, June 28 from the SAP Center in San Jose, California. The betting...",
      "link": "https://www.f4wonline.com/news/aew/aew-x-njpw-forbidden-door-2026-betting-odds-released/",
      "t": "10h",
      "dt": "2026-06-21T19:28:07+00:00"
    },
    {
      "src": "Wrestling Inc",
      "h": "Bully Ray: 'The Death Riders Have Not Helped AEW In Any Way, Shape Or Form'",
      "p": "Bully Ray has some harsh words for AEW's Death Riders.",
      "link": "https://www.wrestlinginc.com/2198476/aew-bully-ray-death-riders-jon-moxley-not-helped-any-way-shape-form/",
      "t": "10h",
      "dt": "2026-06-21T19:27:55+00:00"
    },
    {
      "src": "Wrestling Inc",
      "h": "Matt Sydal Returns To AEW On Collision",
      "p": "Matt Sydal is back on All Elite Wrestling television after a two-year absence stemming from a foot surgery.",
      "link": "https://www.wrestlinginc.com/2198475/matt-sydal-returns-aew-collision/",
      "t": "10h",
      "dt": "2026-06-21T19:07:14+00:00"
    },
    {
      "src": "Wrestling Observer",
      "h": "Injury update on AEW’s Private Party",
      "p": "An update is available on the status of AEW’s Private Party. Neither Isiah Kassidy nor Marq Quen has wrestled since the March 28 edition of AEW Collision, where they lost to the Death Riders team...",
      "link": "https://www.f4wonline.com/news/aew/injury-update-on-aews-private-party-2/",
      "t": "11h",
      "dt": "2026-06-21T18:02:30+00:00"
    }
  ]
}